f3e1e5905acd33c8f397__mypyc.cpython-314t-darwin.so
playa_pdf-0.9.0.dist-info/RECORD
playa_pdf-0.9.0.dist-info/WHEEL
playa_pdf-0.9.0.dist-info/entry_points.txt
playa_pdf-0.9.0.dist-info/METADATA
playa_pdf-0.9.0.dist-info/licenses/LICENSE
playa/pdftypes.py
playa/worker.py
playa/xref.py
playa/color.py
playa/fontprogram.py
playa/miner.py
playa/_version.py
playa/encodings.py
playa/ccitt.py
playa/security.py
playa/image.cpython-314t-darwin.so
playa/__init__.py
playa/page.py
playa/font.py
playa/arcfour.py
playa/parser.py
playa/cmapdb.py
playa/fontmetrics.py
playa/_saslprep.py
playa/content.py
playa/outline.py
playa/cli.py
playa/utils.py
playa/miner.cpython-314t-darwin.so
playa/document.py
playa/structure.py
playa/glyphlist.py
playa/data_structures.py
playa/py.typed
playa/lzw.py
playa/exceptions.py
playa/runlength.py
playa/ascii85.py
playa/interp.py
playa/encodingdb.py
playa/ccitt.cpython-314t-darwin.so
playa/utils.cpython-314t-darwin.so
playa/image.py
playa/cmap/90pv-RKSJ-H.pickle.gz
playa/cmap/83pv-RKSJ-V.pickle.gz
playa/cmap/HKdlb-B5-V.pickle.gz
playa/cmap/HKm314-B5-H.pickle.gz
playa/cmap/78ms-RKSJ-V.pickle.gz
playa/cmap/UniManga-UTF8-V.pickle.gz
playa/cmap/CNS-EUC-H.pickle.gz
playa/cmap/UniKS-UCS2-H.pickle.gz
playa/cmap/KSCpc-EUC-V.pickle.gz
playa/cmap/78-EUC-V.pickle.gz
playa/cmap/UniCNS-UTF16-H.pickle.gz
playa/cmap/UniManga-UTF16-H.pickle.gz
playa/cmap/B5-V.pickle.gz
playa/cmap/78-V.pickle.gz
playa/cmap/GBK-EUC-H.pickle.gz
playa/cmap/Add-RKSJ-V.pickle.gz
playa/cmap/to-unicode-Adobe-Korea1.pickle.gz
playa/cmap/HKgccs-B5-V.pickle.gz
playa/cmap/90ms-RKSJ-H.pickle.gz
playa/cmap/UniJIS2004-UTF32-V.pickle.gz
playa/cmap/EUC-V.pickle.gz
playa/cmap/UniAKR-UTF32-H.pickle.gz
playa/cmap/78-H.pickle.gz
playa/cmap/UniManga-UTF16-V.pickle.gz
playa/cmap/B5-H.pickle.gz
playa/cmap/Add-RKSJ-H.pickle.gz
playa/cmap/GBK-EUC-V.pickle.gz
playa/cmap/90ms-RKSJ-V.pickle.gz
playa/cmap/HKgccs-B5-H.pickle.gz
playa/cmap/UniJIS2004-UTF32-H.pickle.gz
playa/cmap/UniAKR-UTF32-V.pickle.gz
playa/cmap/EUC-H.pickle.gz
playa/cmap/HKdlb-B5-H.pickle.gz
playa/cmap/90pv-RKSJ-V.pickle.gz
playa/cmap/83pv-RKSJ-H.pickle.gz
