Metadata-Version: 2.4
Name: playa-pdf
Version: 0.9.0
Summary: Parallel and LazY Analyzer for PDFs
Project-URL: Homepage, https://dhdaines.github.io/playa
Author-email: David Huggins-Daines <dhd@ecolingui.ca>
License: MIT
License-File: LICENSE
Keywords: pdf parser,text mining
Classifier: Development Status :: 4 - Beta
Classifier: Environment :: Console
Classifier: Intended Audience :: Developers
Classifier: Intended Audience :: Science/Research
Classifier: License :: OSI Approved :: MIT License
Classifier: Programming Language :: Python
Classifier: Programming Language :: Python :: 3 :: Only
Classifier: Programming Language :: Python :: 3.8
Classifier: Programming Language :: Python :: 3.9
Classifier: Programming Language :: Python :: 3.10
Classifier: Programming Language :: Python :: 3.11
Classifier: Programming Language :: Python :: 3.12
Classifier: Programming Language :: Python :: 3.13
Classifier: Programming Language :: Python :: Implementation :: CPython
Classifier: Programming Language :: Python :: Implementation :: PyPy
Classifier: Topic :: Text Processing
Requires-Python: >=3.8
Requires-Dist: mypy-extensions
Provides-Extra: crypto
Requires-Dist: cryptography>=36.0.0; extra == 'crypto'
